{"name":"Rails mirror reflection","tagline":"Rails project to mirror app based on it Database","body":"# ![MirrorBrand](https://raw.githubusercontent.com/MirrorReflection/rails_mirror_reflection/master/modeling/logos/MirrorLogo.min.png)   MirrorReflection\r\n\r\nTODO: Write a gem description\r\n\r\n## Installation\r\n\r\nAdd this line to your application's Gemfile:\r\n\r\n```ruby\r\ngem 'mirror_reflection'\r\n```\r\n\r\nAnd then execute:\r\n\r\n    $ bundle\r\n\r\nOr install it yourself as:\r\n\r\n    $ gem install mirror_reflection\r\n\r\n## Usage\r\n\r\n1. Install the Rails GEM (3.2 or greater)\r\n    * $ gem install rails\r\n2. [Install the MirrorGEM](#installation)\r\n3. __Run__:\r\n    ```ruby\r\n        rake mirror_reflection:new project_name\r\n    ```\r\n__Congratilation!__ your new app mirrored is up.\r\n\r\n## Contributing\r\n\r\n1. Fork it ( https://github.com/[my-github-username]/mirror_reflection/fork )\r\n2. Create your feature branch (`git checkout -b my-new-feature`)\r\n3. Commit your changes (`git commit -am 'Add some feature'`)\r\n4. Push to the branch (`git push origin my-new-feature`)\r\n5. Create a new Pull Request\r\n\r\n## How does it work on the core\r\n![Mirror WorkFlow Diagram](https://raw.githubusercontent.com/MirrorReflection/rails_mirror_reflection/master/modeling/diagrams/Mirror%20-%20WorkFlow.png)\r\n","google":"","note":"Don't delete this file! It's used internally to help with page regeneration."}